[
{"film": "Dust", "annee": "2013", "duree": "8 min", "director": "Ben Ockrent (co-director), Jake Russell (co-director)    ", "note": "7.3", "budget": "None", "benef": "None"},
{"film": "Alice de l'autre c\u00f4t\u00e9 du miroir", "annee": "2016", "duree": "113 min", "director": "James Bobin ", "note": "6.2", "budget": "Budget:$170,000,000(estimated)", "benef": "CumulativeWorldwideGross:$299,457,024"},
{"film": "Le majordome", "annee": "2013", "duree": "132 min", "director": "Lee Daniels ", "note": "7.2", "budget": "Budget:$30,000,000(estimated)", "benef": "CumulativeWorldwideGross:$177,313,795"},
{"film": "Une promesse", "annee": "2013", "duree": "98 min", "director": "Patrice Leconte ", "note": "5.8", "budget": "None", "benef": "CumulativeWorldwideGross:$491,204"},
{"film": "CBGB", "annee": "2013", "duree": "102 min", "director": "Randall Miller ", "note": "6.6", "budget": "Budget:$5,000,000(estimated)", "benef": "CumulativeWorldwideGross:$40,400"},
{"film": "Portraits in Dramatic Time", "annee": "2011", "duree": "None", "director": "David Michalek, Paul Warner ", "note": "7.3", "budget": "None", "benef": "None"},
{"film": "Les jardins du roi", "annee": "2014", "duree": "112 min", "director": "Alan Rickman ", "note": "6.5", "budget": "None", "benef": "CumulativeWorldwideGross:$10,084,623"},
{"film": "The Boy in the Bubble", "annee": "2011", "duree": "None", "director": "Kealan O'Rourke ", "note": "7.3", "budget": "Budget:EUR60,000(estimated)", "benef": "None"},
{"film": "Op\u00e9ration Eye in the Sky", "annee": "2015", "duree": "102 min", "director": "Gavin Hood ", "note": "7.3", "budget": "Budget:$13,000,000(estimated)", "benef": "CumulativeWorldwideGross:$35,259,653"},
{"film": "The Song of Lunch", "annee": "2010", "duree": "50 min", "director": "Niall MacCormick ", "note": "7.5", "budget": "None", "benef": "None"},
{"film": "Harry Potter et les Reliques de la Mort 2\u00e8me partie", "annee": "2011", "duree": "130 min", "director": "David Yates ", "note": "8.1", "budget": "Budget:$125,000,000(estimated)", "benef": "CumulativeWorldwideGross:$1,342,274,154"},
{"film": "Harry Potter et les Reliques de la Mort 1\u00e8re partie", "annee": "2010", "duree": "146 min", "director": "David Yates ", "note": "7.7", "budget": "Budget:GBP150,000,000(estimated)", "benef": "CumulativeWorldwideGross:$977,043,483"},
{"film": "Sonnet Number 12", "annee": "2009", "duree": "2 min", "director": "Helen Piercy ", "note": "8.6", "budget": "None", "benef": "None"},
{"film": "Gambit: Arnaque \u00e0 l'anglaise", "annee": "2012", "duree": "89 min", "director": "Michael Hoffman ", "note": "5.7", "budget": "None", "benef": "CumulativeWorldwideGross:$10,200,000"},
{"film": "The Wildest Dream", "annee": "2010", "duree": "94 min", "director": "Anthony Geffen ", "note": "7.3", "budget": "None", "benef": "CumulativeWorldwideGross:$898,137"},
{"film": "Harry Potter et le Prince de sang-m\u00eal\u00e9", "annee": "2009", "duree": "153 min", "director": "David Yates ", "note": "7.6", "budget": "Budget:$250,000,000(estimated)", "benef": "CumulativeWorldwideGross:$934,454,096"},
{"film": "Alice au pays des merveilles", "annee": "2010", "duree": "108 min", "director": "Tim Burton ", "note": "6.4", "budget": "Budget:$200,000,000(estimated)", "benef": "CumulativeWorldwideGross:$1,025,468,216"},
{"film": "Snow Cake", "annee": "2006", "duree": "112 min", "director": "Marc Evans ", "note": "7.5", "budget": "Budget:EUR3,000,000(estimated)", "benef": "CumulativeWorldwideGross:$1,384,105"},
{"film": "Le Parfum : Histoire d'un meurtrier", "annee": "2006", "duree": "147 min", "director": "Tom Tykwer ", "note": "7.5", "budget": "Budget:$60,000,000(estimated)", "benef": "CumulativeWorldwideGross:$135,039,924"},
{"film": "Bottle Shock", "annee": "2008", "duree": "110 min", "director": "Randall Miller ", "note": "6.8", "budget": "Budget:$5,000,000(estimated)", "benef": "CumulativeWorldwideGross:$4,629,770"},
{"film": "Harry Potter et l'Ordre du Ph\u00e9nix", "annee": "2007", "duree": "138 min", "director": "David Yates ", "note": "7.5", "budget": "Budget:$150,000,000(estimated)", "benef": "CumulativeWorldwideGross:$942,172,396"},
{"film": "Nobel Son", "annee": "2007", "duree": "110 min", "director": "Randall Miller ", "note": "6.2", "budget": "Budget:$4,000,000(estimated)", "benef": "CumulativeWorldwideGross:$550,782"},
{"film": "Sweeney Todd, le diabolique barbier de Fleet Street", "annee": "2007", "duree": "116 min", "director": "Tim Burton ", "note": "7.3", "budget": "Budget:$50,000,000(estimated)", "benef": "CumulativeWorldwideGross:$153,383,627"},
{"film": "La cr\u00e9ation de Dieu", "annee": "2004", "duree": "110 min", "director": "Joseph Sargent ", "note": "8.2", "budget": "None", "benef": "None"},
{"film": "Harry Potter et la Coupe de feu", "annee": "2005", "duree": "157 min", "director": "Mike Newell ", "note": "7.7", "budget": "Budget:$150,000,000(estimated)", "benef": "CumulativeWorldwideGross:$896,462,886"},
{"film": "Harry Potter et le Prisonnier d'Azkaban", "annee": "2004", "duree": "142 min", "director": "Alfonso Cuar\u00f3n ", "note": "7.9", "budget": "Budget:$130,000,000(estimated)", "benef": "CumulativeWorldwideGross:$796,246,544"},
{"film": "Love Actually", "annee": "2003", "duree": "135 min", "director": "Richard Curtis ", "note": "7.6", "budget": "Budget:$40,000,000(estimated)", "benef": "CumulativeWorldwideGross:$245,203,167"},
{"film": "H2G2 : Le Guide du voyageur galactique", "annee": "2005", "duree": "109 min", "director": "Garth Jennings ", "note": "6.8", "budget": "Budget:$50,000,000(estimated)", "benef": "CumulativeWorldwideGross:$104,478,416"},
{"film": "The Search for John Gissing", "annee": "2001", "duree": "91 min", "director": "Mike Binder ", "note": "6.8", "budget": "None", "benef": "None"},
{"film": "Harry Potter et la Chambre des secrets", "annee": "2002", "duree": "161 min", "director": "Chris Columbus ", "note": "7.4", "budget": "Budget:$100,000,000(estimated)", "benef": "CumulativeWorldwideGross:$879,602,366"},
{"film": "Play", "annee": "2001", "duree": "None", "director": "Anthony Minghella ", "note": "7.7", "budget": "None", "benef": "None"},
{"film": "Harry Potter \u00e0 l'\u00e9cole des sorciers", "annee": "2001", "duree": "152 min", "director": "Chris Columbus ", "note": "7.6", "budget": "Budget:$125,000,000(estimated)", "benef": "CumulativeWorldwideGross:$1,006,968,171"},
{"film": "Texas: In Demand", "annee": "2000", "duree": "4 min", "director": "Vaughan Arnell (uncredited)    ", "note": "8.5", "budget": "None", "benef": "None"},
{"film": "Coup de peigne", "annee": "2001", "duree": "94 min", "director": "Paddy Breathnach ", "note": "6.3", "budget": "None", "benef": "CumulativeWorldwideGross:$830,286"},
{"film": "We Know Where You Live", "annee": "2001", "duree": "94 min", "director": "Declan Lowney ", "note": "6.8", "budget": "None", "benef": "None"},
{"film": "Gloups! Je suis un poisson", "annee": "2000", "duree": "80 min", "director": "Stefan Fjeldmark, Greg Manwaring |2 more credits\u00a0\u00bb    ", "note": "6.0", "budget": "None", "benef": "CumulativeWorldwideGross:$5,595,327"},
{"film": "Galaxy Quest", "annee": "1999", "duree": "102 min", "director": "Dean Parisot ", "note": "7.3", "budget": "Budget:$45,000,000(estimated)", "benef": "CumulativeWorldwideGross:$90,683,916"},
{"film": "L'invit\u00e9e de l'hiver", "annee": "1997", "duree": "108 min", "director": "Alan Rickman ", "note": "7.0", "budget": "None", "benef": "CumulativeWorldwideGross:$870,290"},
{"film": "Dogma", "annee": "1999", "duree": "130 min", "director": "Kevin Smith ", "note": "7.3", "budget": "Budget:$10,000,000(estimated)", "benef": "CumulativeWorldwideGross:$31,429,330"},
{"film": "Michael Collins", "annee": "1996", "duree": "133 min", "director": "Neil Jordan ", "note": "7.2", "budget": "Budget:$25,000,000(estimated)", "benef": "CumulativeWorldwideGross:$11,135,803"},
{"film": "Mesmer", "annee": "1994", "duree": "107 min", "director": "Roger Spottiswoode ", "note": "6.1", "budget": "Budget:GBP5,600,000(estimated)", "benef": "None"},
{"film": "Judas Kiss", "annee": "1998", "duree": "98 min", "director": "Sebastian Gutierrez ", "note": "6.1", "budget": "None", "benef": "None"},
{"film": "An Awfully Big Adventure", "annee": "1995", "duree": "112 min", "director": "Mike Newell ", "note": "6.0", "budget": "Budget:$4,000,000(estimated)", "benef": "CumulativeWorldwideGross:$259,724"},
{"film": "Raison et sentiments", "annee": "1995", "duree": "136 min", "director": "Ang Lee ", "note": "7.6", "budget": "Budget:$16,000,000(estimated)", "benef": "CumulativeWorldwideGross:$134,582,776"},
{"film": "Dark Harbor", "annee": "1998", "duree": "96 min", "director": "Adam Coleman Howard ", "note": "6.2", "budget": "None", "benef": "None"},
{"film": "Rasputin", "annee": "1996", "duree": "135 min", "director": "Uli Edel ", "note": "7.1", "budget": "None", "benef": "None"},
{"film": "Close My Eyes", "annee": "1991", "duree": "108 min", "director": "Stephen Poliakoff ", "note": "6.3", "budget": "None", "benef": "CumulativeWorldwideGross:$135,893"},
{"film": "Robin des bois: Prince des voleurs", "annee": "1991", "duree": "143 min", "director": "Kevin Reynolds ", "note": "6.9", "budget": "Budget:$48,000,000(estimated)", "benef": "CumulativeWorldwideGross:$390,493,908"},
{"film": "Mr Quigley l'Australien", "annee": "1990", "duree": "119 min", "director": "Simon Wincer ", "note": "6.9", "budget": "Budget:$20,000,000(estimated)", "benef": "CumulativeWorldwideGross:$21,413,105"},
{"film": "Closet Land", "annee": "1991", "duree": "None", "director": "Radha Bharadwaj ", "note": "7.0", "budget": "Budget:$4,000,000(estimated)", "benef": "CumulativeWorldwideGross:$259,012"},
{"film": "Lumi\u00e8re et compagnie", "annee": "1995", "duree": "88 min", "director": "Theodoros Angelopoulos (as Theo Angelopoulos), Vicente Aranda |39 more credits\u00a0\u00bb    ", "note": "6.9", "budget": "None", "benef": "None"},
{"film": "Bob Roberts", "annee": "1992", "duree": "102 min", "director": "Tim Robbins ", "note": "7.0", "budget": "None", "benef": "CumulativeWorldwideGross:$4,479,470"},
{"film": "Truly Madly Deeply", "annee": "1990", "duree": "106 min", "director": "Anthony Minghella ", "note": "7.2", "budget": "None", "benef": "CumulativeWorldwideGross:$1,554,742"},
{"film": "Revolutionary Witness: The Preacher", "annee": "1989", "duree": "20 min", "director": "Jonathan Dent ", "note": "8.8", "budget": "None", "benef": "None"},
{"film": "Busted", "annee": "1983", "duree": "None", "director": "Jon Amiel ", "note": "7.5", "budget": "None", "benef": "None"},
{"film": "Calendrier meurtrier", "annee": "1989", "duree": "97 min", "director": "Pat O'Connor ", "note": "5.6", "budget": "None", "benef": "CumulativeWorldwideGross:$4,611,062"},
{"film": "Wetherby", "annee": "1985", "duree": "None", "director": "David Hare ", "note": "6.8", "budget": "None", "benef": "CumulativeWorldwideGross:$1,299,985"},
{"film": "Pi\u00e8ge de cristal", "annee": "1988", "duree": "132 min", "director": "John McTiernan ", "note": "8.2", "budget": "Budget:$28,000,000(estimated)", "benef": "CumulativeWorldwideGross:$141,603,197"},
{"film": "The Barchester Chronicles", "annee": "1982", "duree": "385 min", "director": "Donald Pleasence, Janet Maw, Nigel Hawthorne |See full cast & crew\u00a0\u00bb    ", "note": "8.0", "budget": "None", "benef": "None"},
{"film": "Th\u00e9r\u00e8se Raquin", "annee": "1980", "duree": "173 min", "director": "Kate Nelligan, Mona Washbourne, Brian Cox |See full cast & crew\u00a0\u00bb    ", "note": "7.4", "budget": "None", "benef": "None"},
{"film": "Romeo & Juliet", "annee": "1978", "duree": "None", "director": "Alvin Rakoff ", "note": "6.7", "budget": "None", "benef": "None"},
{"film": "La taupe", "annee": "1982", "duree": "60 min", "director": "Alec Guinness, Eileen Atkins, Bill Paterson |See full cast & crew\u00a0\u00bb    ", "note": "8.6", "budget": "None", "benef": "None"}
]