[
{"film": "Equalizer 2", "annee": "2018", "duree": "121 min", "director": "Antoine Fuqua ", "note": "6.7", "budget": "Budget:$62,000,000(estimated)", "benef": "CumulativeWorldwideGross:$190,400,157"},
{"film": "L'Affaire Roman J.", "annee": "2017", "duree": "122 min", "director": "Dan Gilroy ", "note": "6.5", "budget": "Budget:$22,000,000(estimated)", "benef": "CumulativeWorldwideGross:$13,025,860"},
{"film": "Fences", "annee": "2016", "duree": "139 min", "director": "Denzel Washington ", "note": "7.2", "budget": "Budget:$24,000,000(estimated)", "benef": "CumulativeWorldwideGross:$64,414,761"},
{"film": "Une affaire de d\u00e9tails", "annee": "2021", "duree": "128 min", "director": "John Lee Hancock ", "note": "6.3", "budget": "None", "benef": "CumulativeWorldwideGross:$29,755,000"},
{"film": "Les sept mercenaires", "annee": "2016", "duree": "132 min", "director": "Antoine Fuqua ", "note": "6.9", "budget": "Budget:$90,000,000(estimated)", "benef": "CumulativeWorldwideGross:$162,360,636"},
{"film": "2 Guns", "annee": "2013", "duree": "109 min", "director": "Baltasar Korm\u00e1kur ", "note": "6.7", "budget": "Budget:$61,000,000(estimated)", "benef": "CumulativeWorldwideGross:$131,940,411"},
{"film": "Equalizer", "annee": "2014", "duree": "132 min", "director": "Antoine Fuqua ", "note": "7.2", "budget": "Budget:$55,000,000(estimated)", "benef": "CumulativeWorldwideGross:$192,330,738"},
{"film": "Flight", "annee": "2012", "duree": "138 min", "director": "Robert Zemeckis ", "note": "7.3", "budget": "Budget:$31,000,000(estimated)", "benef": "CumulativeWorldwideGross:$161,772,375"},
{"film": "S\u00e9curit\u00e9 rapproch\u00e9e", "annee": "2012", "duree": "115 min", "director": "Daniel Espinosa ", "note": "6.7", "budget": "Budget:$85,000,000(estimated)", "benef": "CumulativeWorldwideGross:$208,076,205"},
{"film": "Unstoppable", "annee": "2010", "duree": "98 min", "director": "Tony Scott ", "note": "6.8", "budget": "Budget:$100,000,000(estimated)", "benef": "CumulativeWorldwideGross:$167,805,466"},
{"film": "Le Livre d'Eli", "annee": "2010", "duree": "118 min", "director": "Albert Hughes (as The Hughes Brothers), Allen Hughes (as The Hughes Brothers)    ", "note": "6.9", "budget": "Budget:$80,000,000(estimated)", "benef": "CumulativeWorldwideGross:$157,107,755"},
{"film": "L'attaque du m\u00e9tro 123", "annee": "2009", "duree": "106 min", "director": "Tony Scott ", "note": "6.4", "budget": "Budget:$100,000,000(estimated)", "benef": "CumulativeWorldwideGross:$150,166,126"},
{"film": "The Great Debaters", "annee": "2007", "duree": "126 min", "director": "Denzel Washington ", "note": "7.5", "budget": "Budget:$15,000,000(estimated)", "benef": "CumulativeWorldwideGross:$30,271,556"},
{"film": "Man on Fire", "annee": "2004", "duree": "146 min", "director": "Tony Scott ", "note": "7.7", "budget": "Budget:$70,000,000(estimated)", "benef": "CumulativeWorldwideGross:$130,834,852"},
{"film": "American Gangster", "annee": "2007", "duree": "157 min", "director": "Ridley Scott ", "note": "7.8", "budget": "Budget:$100,000,000(estimated)", "benef": "CumulativeWorldwideGross:$269,755,430"},
{"film": "Un crime dans la t\u00eate", "annee": "2004", "duree": "129 min", "director": "Jonathan Demme ", "note": "6.6", "budget": "Budget:$80,000,000(estimated)", "benef": "CumulativeWorldwideGross:$96,105,910"},
{"film": "Inside Man - L'homme de l'int\u00e9rieur", "annee": "2006", "duree": "129 min", "director": "Spike Lee ", "note": "7.6", "budget": "Budget:$45,000,000(estimated)", "benef": "CumulativeWorldwideGross:$186,003,591"},
{"film": "D\u00e9j\u00e0 vu", "annee": "2006", "duree": "126 min", "director": "Tony Scott ", "note": "7.1", "budget": "Budget:$75,000,000(estimated)", "benef": "CumulativeWorldwideGross:$180,557,550"},
{"film": "Antwone Fisher", "annee": "2002", "duree": "120 min", "director": "Denzel Washington ", "note": "7.3", "budget": "Budget:$12,500,000(estimated)", "benef": "CumulativeWorldwideGross:$23,367,586"},
{"film": "John Q", "annee": "2002", "duree": "116 min", "director": "Nick Cassavetes ", "note": "7.1", "budget": "Budget:$36,000,000(estimated)", "benef": "CumulativeWorldwideGross:$102,244,770"},
{"film": "Out of Time", "annee": "2003", "duree": "105 min", "director": "Carl Franklin ", "note": "6.5", "budget": "Budget:$50,000,000(estimated)", "benef": "CumulativeWorldwideGross:$55,495,563"},
{"film": "Training Day", "annee": "2001", "duree": "122 min", "director": "Antoine Fuqua ", "note": "7.7", "budget": "Budget:$45,000,000(estimated)", "benef": "CumulativeWorldwideGross:$104,876,233"},
{"film": "Bone Collector", "annee": "1999", "duree": "118 min", "director": "Phillip Noyce ", "note": "6.7", "budget": "Budget:$73,000,000(estimated)", "benef": "CumulativeWorldwideGross:$151,493,655"},
{"film": "Le plus beau des combats", "annee": "2000", "duree": "113 min", "director": "Boaz Yakin ", "note": "7.8", "budget": "Budget:$30,000,000(estimated)", "benef": "CumulativeWorldwideGross:$136,771,683"},
{"film": "Hurricane Carter", "annee": "1999", "duree": "146 min", "director": "Norman Jewison ", "note": "7.6", "budget": "Budget:$50,000,000(estimated)", "benef": "CumulativeWorldwideGross:$73,956,241"},
{"film": "Couvre-feu", "annee": "1998", "duree": "116 min", "director": "Edward Zwick ", "note": "6.4", "budget": "Budget:$70,000,000(estimated)", "benef": "CumulativeWorldwideGross:$116,672,912"},
{"film": "He Got Game", "annee": "1998", "duree": "136 min", "director": "Spike Lee ", "note": "6.9", "budget": "Budget:$25,000,000(estimated)", "benef": "CumulativeWorldwideGross:$21,567,853"},
{"film": "Le t\u00e9moin du mal", "annee": "1998", "duree": "124 min", "director": "Gregory Hoblit ", "note": "7.0", "budget": "None", "benef": "CumulativeWorldwideGross:$25,232,289"},
{"film": "Mother Goose: A Rappin' and Rhymin' Special", "annee": "1997", "duree": "34 min", "director": "Barry Douglas ", "note": "5.6", "budget": "None", "benef": "None"},
{"film": "Programm\u00e9 pour tuer", "annee": "1995", "duree": "106 min", "director": "Brett Leonard ", "note": "5.6", "budget": "Budget:$30,000,000(estimated)", "benef": "CumulativeWorldwideGross:$24,047,675"},
{"film": "La femme du pasteur", "annee": "1996", "duree": "123 min", "director": "Penny Marshall ", "note": "5.6", "budget": "Budget:$40,000,000(estimated)", "benef": "CumulativeWorldwideGross:$48,102,795"},
{"film": "\u00c0 l'\u00e9preuve du feu", "annee": "1996", "duree": "116 min", "director": "Edward Zwick ", "note": "6.6", "budget": "Budget:$46,000,000(estimated)", "benef": "CumulativeWorldwideGross:$100,860,818"},
{"film": "USS Alabama", "annee": "1995", "duree": "116 min", "director": "Tony Scott ", "note": "7.3", "budget": "Budget:$53,000,000(estimated)", "benef": "CumulativeWorldwideGross:$157,387,195"},
{"film": "Philadelphia", "annee": "1993", "duree": "125 min", "director": "Jonathan Demme ", "note": "7.7", "budget": "Budget:$26,000,000(estimated)", "benef": "CumulativeWorldwideGross:$206,678,440"},
{"film": "Le diable en robe bleue", "annee": "1995", "duree": "102 min", "director": "Carl Franklin ", "note": "6.7", "budget": "Budget:$27,000,000(estimated)", "benef": "CumulativeWorldwideGross:$16,140,822"},
{"film": "L'affaire P\u00e9lican", "annee": "1993", "duree": "141 min", "director": "Alan J. Pakula ", "note": "6.6", "budget": "Budget:$45,000,000(estimated)", "benef": "CumulativeWorldwideGross:$195,268,056"},
{"film": "Mo' Better Blues", "annee": "1990", "duree": "129 min", "director": "Spike Lee ", "note": "6.6", "budget": "Budget:$10,000,000(estimated)", "benef": "CumulativeWorldwideGross:$16,153,593"},
{"film": "Mississippi Masala", "annee": "1991", "duree": "118 min", "director": "Mira Nair ", "note": "6.6", "budget": "None", "benef": "CumulativeWorldwideGross:$7,308,786"},
{"film": "Malcolm X", "annee": "1992", "duree": "202 min", "director": "Spike Lee ", "note": "7.7", "budget": "Budget:$33,000,000(estimated)", "benef": "CumulativeWorldwideGross:$48,169,910"},
{"film": "Beaucoup de bruit pour rien", "annee": "1993", "duree": "111 min", "director": "Kenneth Branagh ", "note": "7.3", "budget": "Budget:$11,000,000(estimated)", "benef": "CumulativeWorldwideGross:$22,549,338"},
{"film": "Ricochet", "annee": "1991", "duree": "102 min", "director": "Russell Mulcahy ", "note": "6.2", "budget": "None", "benef": "CumulativeWorldwideGross:$21,756,163"},
{"film": "Glory", "annee": "1989", "duree": "122 min", "director": "Edward Zwick ", "note": "7.8", "budget": "Budget:$18,000,000(estimated)", "benef": "CumulativeWorldwideGross:$26,979,166"},
{"film": "The Mighty Quinn", "annee": "1989", "duree": "98 min", "director": "Carl Schenkel ", "note": "6.0", "budget": "None", "benef": "CumulativeWorldwideGross:$4,557,214"},
{"film": "Pour la gloire", "annee": "1988", "duree": "105 min", "director": "Martin Stellman ", "note": "5.6", "budget": "None", "benef": "CumulativeWorldwideGross:$191,051"},
{"film": "Un ange de trop", "annee": "1990", "duree": "100 min", "director": "James D. Parriott ", "note": "5.6", "budget": "None", "benef": "CumulativeWorldwideGross:$4,134,992"},
{"film": "Danger \u00e0 l'universit\u00e9", "annee": "1986", "duree": "None", "director": "Eric Laneuville ", "note": "6.1", "budget": "None", "benef": "None"},
{"film": "Cry Freedom - Le cri de la libert\u00e9", "annee": "1987", "duree": "157 min", "director": "Richard Attenborough ", "note": "7.4", "budget": "Budget:$29,000,000(estimated)", "benef": "CumulativeWorldwideGross:$5,899,797"},
{"film": "Les coulisses du pouvoir", "annee": "1986", "duree": "111 min", "director": "Sidney Lumet ", "note": "5.7", "budget": "Budget:$16,000,000(estimated)", "benef": "CumulativeWorldwideGross:$3,800,000"},
{"film": "Coriolanus", "annee": "1979", "duree": "None", "director": "Wilford Leach ", "note": "6.8", "budget": "None", "benef": "None"},
{"film": "Soldier's Story", "annee": "1984", "duree": "101 min", "director": "Norman Jewison ", "note": "7.2", "budget": "Budget:$6,000,000(estimated)", "benef": "CumulativeWorldwideGross:$21,821,347"},
{"film": "Carbon Copy", "annee": "1981", "duree": "92 min", "director": "Michael Schultz ", "note": "5.7", "budget": "Budget:$6,000,000(estimated)", "benef": "CumulativeWorldwideGross:$9,566,593"},
{"film": "Flesh & Blood", "annee": "1979", "duree": "240 min", "director": "Jud Taylor ", "note": "6.5", "budget": "None", "benef": "None"},
{"film": "Wilma", "annee": "1977", "duree": "100 min", "director": "Bud Greenspan ", "note": "6.1", "budget": "None", "benef": "None"},
{"film": "L'amour bris\u00e9", "annee": "1984", "duree": "96 min", "director": "Jud Taylor ", "note": "5.5", "budget": "None", "benef": "None"}
]