[
{"film": "Vishal Dadlani & Benny Dayal: Jai Jai Shivshankar", "annee": "2019", "duree": "2 min", "director": "Vishal Dadlani, Benny Dayal, Hrithik Roshan |See full cast & crew\u00a0\u00bb    ", "note": "7.9", "budget": "None", "benef": "None"},
{"film": "Arijit Singh & Shilpa Rao: Ghungroo", "annee": "2019", "duree": "2 min", "director": "Luca De Falco ", "note": "8.5", "budget": "None", "benef": "None"},
{"film": "War", "annee": "2019", "duree": "154 min", "director": "Siddharth Anand ", "note": "6.5", "budget": "Budget:$21,000,000(estimated)", "benef": "CumulativeWorldwideGross:$67,179,155"},
{"film": "Super 30", "annee": "2019", "duree": "154 min", "director": "Vikas Bahl ", "note": "7.9", "budget": "None", "benef": "CumulativeWorldwideGross:$24,701,637"},
{"film": "Kaabil", "annee": "2017", "duree": "None", "director": "Sanjay Gupta ", "note": "7.1", "budget": "None", "benef": "CumulativeWorldwideGross:$21,893,244"},
{"film": "Prem Areni, Janardan Dhatrak, Divya Kumar, Chaitally Parmar: Basanti No Dance", "annee": "2019", "duree": "3 min", "director": "Prem Areni, Janardan Dhatrak, Divya Kumar |See full cast & crew\u00a0\u00bb    ", "note": "7.0", "budget": "None", "benef": "None"},
{"film": "Bang Bang", "annee": "2014", "duree": "153 min", "director": "Siddharth Anand ", "note": "5.5", "budget": "None", "benef": "CumulativeWorldwideGross:$42,045,981"},
{"film": "Krrish 3", "annee": "2013", "duree": "152 min", "director": "Rakesh Roshan ", "note": "5.2", "budget": "Budget:INR1,150,000,000(estimated)", "benef": "CumulativeWorldwideGross:$4,170,204"},
{"film": "Hey Bro", "annee": "2015", "duree": "113 min", "director": "Ajay Chandhok ", "note": "3.0", "budget": "None", "benef": "CumulativeWorldwideGross:$323,930"},
{"film": "Mohenjo Daro", "annee": "2016", "duree": "155 min", "director": "Ashutosh Gowariker ", "note": "5.7", "budget": "None", "benef": "CumulativeWorldwideGross:$1,630,231"},
{"film": "Agneepath", "annee": "2012", "duree": "174 min", "director": "Karan Malhotra ", "note": "6.9", "budget": "Budget:INR600,000,000(estimated)", "benef": "CumulativeWorldwideGross:$26,001,696"},
{"film": "Don, le retour du roi", "annee": "2011", "duree": "148 min", "director": "Farhan Akhtar ", "note": "7.1", "budget": "Budget:$16,700,000(estimated)", "benef": "CumulativeWorldwideGross:$6,913,518"},
{"film": "On ne vit qu'une seule fois", "annee": "2011", "duree": "155 min", "director": "Zoya Akhtar ", "note": "8.2", "budget": "Budget:INR550,000,000(estimated)", "benef": "CumulativeWorldwideGross:$5,192,743"},
{"film": "Guzaarish", "annee": "2010", "duree": "126 min", "director": "Sanjay Leela Bhansali ", "note": "7.4", "budget": "None", "benef": "CumulativeWorldwideGross:$7,564,310"},
{"film": "Luck by Chance", "annee": "2009", "duree": "156 min", "director": "Zoya Akhtar ", "note": "7.1", "budget": "None", "benef": "CumulativeWorldwideGross:$4,504,365"},
{"film": "I See You", "annee": "2006", "duree": "122 min", "director": "Vivek b Agrawal ", "note": "4.1", "budget": "None", "benef": "CumulativeWorldwideGross:$629,508"},
{"film": "Jodhaa Akbar", "annee": "2008", "duree": "213 min", "director": "Ashutosh Gowariker ", "note": "7.6", "budget": "Budget:INR400,000,000(estimated)", "benef": "CumulativeWorldwideGross:$26,935,618"},
{"film": "Lakshya", "annee": "2004", "duree": "186 min", "director": "Farhan Akhtar ", "note": "7.9", "budget": "Budget:INR300,000,000(estimated)", "benef": "CumulativeWorldwideGross:$5,859,242"},
{"film": "Kites", "annee": "2010", "duree": "123 min", "director": "Anurag Basu ", "note": "6.1", "budget": "Budget:INR600,000,000(estimated)", "benef": "CumulativeWorldwideGross:$11,906,497"},
{"film": "Krrish", "annee": "2006", "duree": "185 min", "director": "Rakesh Roshan ", "note": "6.4", "budget": "Budget:$10,200,000(estimated)", "benef": "CumulativeWorldwideGross:$18,041,250"},
{"film": "Dhoom:2", "annee": "2006", "duree": "152 min", "director": "Sanjay Gadhvi ", "note": "6.5", "budget": "Budget:INR350,000,000(estimated)", "benef": "CumulativeWorldwideGross:$32,396,427"},
{"film": "Main Prem Ki Diwani Hoon", "annee": "2003", "duree": "197 min", "director": "Sooraj R. Barjatya ", "note": "4.0", "budget": "Budget:INR300,000,000(estimated)", "benef": "CumulativeWorldwideGross:$6,290,342"},
{"film": "Koi... Mil Gaya", "annee": "2003", "duree": "171 min", "director": "Rakesh Roshan ", "note": "7.1", "budget": "Budget:INR350,000,000(estimated)", "benef": "CumulativeWorldwideGross:$12,168,232"},
{"film": "Mujhse Dosti Karoge!", "annee": "2002", "duree": "149 min", "director": "Kunal Kohli ", "note": "5.1", "budget": "Budget:INR170,000,000(estimated)", "benef": "CumulativeWorldwideGross:$932,648"},
{"film": "La famille indienne", "annee": "2001", "duree": "210 min", "director": "Karan Johar ", "note": "7.4", "budget": "Budget:$7,500,000(estimated)", "benef": "CumulativeWorldwideGross:$11,334,547"},
{"film": "Na Tum Jaano Na Hum", "annee": "2002", "duree": "158 min", "director": "Arjun Sablok ", "note": "5.0", "budget": "Budget:INR180,000,000(estimated)", "benef": "CumulativeWorldwideGross:$251,877"},
{"film": "Aap Mujhe Achche Lagne Lage", "annee": "2002", "duree": "180 min", "director": "Vikram Bhatt ", "note": "3.1", "budget": "Budget:INR115,000,000(estimated)", "benef": "None"},
{"film": "Yaadein...", "annee": "2001", "duree": "171 min", "director": "Subhash Ghai ", "note": "4.4", "budget": "Budget:INR160,000,000(estimated)", "benef": "CumulativeWorldwideGross:$1,093,819"},
{"film": "Mission Kashmir", "annee": "2000", "duree": "154 min", "director": "Vidhu Vinod Chopra ", "note": "6.7", "budget": "None", "benef": "None"},
{"film": "Fiza", "annee": "2000", "duree": "170 min", "director": "Khalid Mohamed ", "note": "6.1", "budget": "Budget:$1,000,000(estimated)", "benef": "CumulativeWorldwideGross:$596,591"},
{"film": "Kaho Naa... Pyaar Hai", "annee": "2000", "duree": "172 min", "director": "Rakesh Roshan ", "note": "6.9", "budget": "Budget:INR140,000,000(estimated)", "benef": "None"},
{"film": "Aasra Pyaar Da", "annee": "1983", "duree": "150 min", "director": "J. Om Prakash ", "note": "7.4", "budget": "None", "benef": "None"},
{"film": "Aap Ke Deewane", "annee": "1980", "duree": "None", "director": "Surendra Mohan ", "note": "5.8", "budget": "None", "benef": "None"},
{"film": "Bhagwaan Dada", "annee": "1986", "duree": "147 min", "director": "J. Om Prakash ", "note": "4.3", "budget": "None", "benef": "None"},
{"film": "Akarshan", "annee": "1988", "duree": "None", "director": "Tanvir Ahmed ", "note": "5.0", "budget": "None", "benef": "None"},
{"film": "Aas Paas", "annee": "1981", "duree": "None", "director": "J. Om Prakash ", "note": "5.9", "budget": "None", "benef": "None"},
{"film": "Aasha", "annee": "1980", "duree": "123 min", "director": "J. Om Prakash ", "note": "5.3", "budget": "None", "benef": "None"}
]