[
{"film": "Conspiracy", "annee": "2017", "duree": "98 min", "director": "Michael Apted ", "note": "6.3", "budget": "None", "benef": "CumulativeWorldwideGross:$4,699,125"},
{"film": "Unbreaking America: Divided We Fall", "annee": "2019", "duree": "10 min", "director": "Michael Marantz ", "note": "7.9", "budget": "None", "benef": "None"},
{"film": "Dong wu shi jie", "annee": "2018", "duree": "132 min", "director": "Yan Han ", "note": "6.5", "budget": "None", "benef": "CumulativeWorldwideGross:$74,922,830"},
{"film": "Ant-Man", "annee": "2015", "duree": "117 min", "director": "Peyton Reed ", "note": "7.3", "budget": "Budget:$130,000,000(estimated)", "benef": "CumulativeWorldwideGross:$519,311,965"},
{"film": "Hors de port\u00e9e", "annee": "2014", "duree": "91 min", "director": "Jean-Baptiste L\u00e9onetti ", "note": "5.6", "budget": "None", "benef": "CumulativeWorldwideGross:$1,100,432"},
{"film": "Ainsi va la vie", "annee": "2014", "duree": "94 min", "director": "Rob Reiner ", "note": "5.8", "budget": "Budget:$18,000,000(estimated)", "benef": "CumulativeWorldwideGross:$25,419,147"},
{"film": "Last Vegas", "annee": "2013", "duree": "105 min", "director": "Jon Turteltaub ", "note": "6.6", "budget": "Budget:$28,000,000(estimated)", "benef": "CumulativeWorldwideGross:$134,409,025"},
{"film": "Ant-Man et la Gu\u00eape", "annee": "2018", "duree": "118 min", "director": "Peyton Reed ", "note": "7.0", "budget": "Budget:$162,000,000(estimated)", "benef": "CumulativeWorldwideGross:$622,674,139"},
{"film": "Pi\u00e9g\u00e9e", "annee": "2011", "duree": "93 min", "director": "Steven Soderbergh ", "note": "5.8", "budget": "Budget:$23,000,000(estimated)", "benef": "CumulativeWorldwideGross:$34,513,760"},
{"film": "Ma vie avec Liberace", "annee": "2013", "duree": "118 min", "director": "Steven Soderbergh ", "note": "7.0", "budget": "Budget:$23,000,000(estimated)", "benef": "CumulativeWorldwideGross:$13,352,609"},
{"film": "Solitary Man", "annee": "2009", "duree": "90 min", "director": "Brian Koppelman, David Levien ", "note": "6.3", "budget": "Budget:$15,000,000(estimated)", "benef": "CumulativeWorldwideGross:$5,682,554"},
{"film": "Avengers: Endgame", "annee": "2019", "duree": "181 min", "director": "Anthony Russo, Joe Russo ", "note": "8.4", "budget": "Budget:$356,000,000(estimated)", "benef": "CumulativeWorldwideGross:$2,797,501,328"},
{"film": "Pr\u00e9sum\u00e9 coupable", "annee": "2009", "duree": "106 min", "director": "Peter Hyams ", "note": "5.9", "budget": "Budget:$25,000,000(estimated)", "benef": "CumulativeWorldwideGross:$4,515,258"},
{"film": "Hant\u00e9 par ses ex", "annee": "2009", "duree": "115 min", "director": "Mark Waters ", "note": "5.8", "budget": "Budget:$37,500,000(estimated)", "benef": "CumulativeWorldwideGross:$102,366,815"},
{"film": "Wall Street: l'argent ne dort jamais", "annee": "2010", "duree": "133 min", "director": "Oliver Stone ", "note": "6.2", "budget": "Budget:$70,000,000(estimated)", "benef": "CumulativeWorldwideGross:$134,748,021"},
{"film": "King of California", "annee": "2007", "duree": "93 min", "director": "Michael A. Cahill (as Mike Cahill)    ", "note": "6.6", "budget": "Budget:$10,000,000(estimated)", "benef": "CumulativeWorldwideGross:$1,045,786"},
{"film": "The Sentinel", "annee": "2006", "duree": "108 min", "director": "Clark Johnson ", "note": "6.1", "budget": "Budget:$60,000,000(estimated)", "benef": "CumulativeWorldwideGross:$78,810,595"},
{"film": "Toi et Moi... et Dupr\u00e9e", "annee": "2006", "duree": "110 min", "director": "Anthony Russo, Joe Russo ", "note": "5.6", "budget": "Budget:$54,000,000(estimated)", "benef": "CumulativeWorldwideGross:$130,628,903"},
{"film": "Une si belle famille", "annee": "2003", "duree": "None", "director": "Fred Schepisi ", "note": "5.6", "budget": "None", "benef": "CumulativeWorldwideGross:$8,211,508"},
{"film": "Pas un mot...", "annee": "2001", "duree": "113 min", "director": "Gary Fleder ", "note": "6.3", "budget": "Budget:$50,000,000(estimated)", "benef": "CumulativeWorldwideGross:$100,020,092"},
{"film": "Bob Dylan: Things Have Changed", "annee": "2000", "duree": "5 min", "director": "Curtis Hanson ", "note": "7.3", "budget": "None", "benef": "None"},
{"film": "Traffic", "annee": "2000", "duree": "147 min", "director": "Steven Soderbergh ", "note": "7.6", "budget": "Budget:$48,000,000(estimated)", "benef": "CumulativeWorldwideGross:$207,515,725"},
{"film": "Divine mais dangereuse", "annee": "2001", "duree": "93 min", "director": "Harald Zwart ", "note": "6.1", "budget": "Budget:$18,000,000(estimated)", "benef": "CumulativeWorldwideGross:$13,578,186"},
{"film": "The Game", "annee": "1997", "duree": "129 min", "director": "David Fincher ", "note": "7.8", "budget": "Budget:$50,000,000(estimated)", "benef": "CumulativeWorldwideGross:$109,423,648"},
{"film": "Meurtre parfait", "annee": "1998", "duree": "107 min", "director": "Andrew Davis ", "note": "6.5", "budget": "Budget:$60,000,000(estimated)", "benef": "CumulativeWorldwideGross:$128,038,368"},
{"film": "Espion mais pas trop!", "annee": "2003", "duree": "98 min", "director": "Andrew Fleming ", "note": "5.8", "budget": "Budget:$40,000,000(estimated)", "benef": "CumulativeWorldwideGross:$26,891,849"},
{"film": "Harc\u00e8lement", "annee": "1994", "duree": "128 min", "director": "Barry Levinson ", "note": "6.1", "budget": "Budget:$55,000,000(estimated)", "benef": "CumulativeWorldwideGross:$214,015,089"},
{"film": "Wonder Boys", "annee": "2000", "duree": "107 min", "director": "Curtis Hanson ", "note": "7.2", "budget": "Budget:$55,000,000(estimated)", "benef": "CumulativeWorldwideGross:$33,426,588"},
{"film": "L'ombre et la proie", "annee": "1996", "duree": "110 min", "director": "Stephen Hopkins ", "note": "6.9", "budget": "Budget:$55,000,000(estimated)", "benef": "CumulativeWorldwideGross:$38,619,405"},
{"film": "Le pr\u00e9sident et Miss Wade", "annee": "1995", "duree": "114 min", "director": "Rob Reiner ", "note": "6.8", "budget": "Budget:$62,000,000(estimated)", "benef": "CumulativeWorldwideGross:$107,879,496"},
{"film": "Basic Instinct", "annee": "1992", "duree": "127 min", "director": "Paul Verhoeven ", "note": "7.0", "budget": "Budget:$49,000,000(estimated)", "benef": "CumulativeWorldwideGross:$352,927,224"},
{"film": "Chute libre", "annee": "1993", "duree": "113 min", "director": "Joel Schumacher ", "note": "7.6", "budget": "Budget:$25,000,000(estimated)", "benef": "CumulativeWorldwideGross:$40,903,593"},
{"film": "La guerre des Rose", "annee": "1989", "duree": "116 min", "director": "Danny DeVito ", "note": "6.9", "budget": "Budget:$26,000,000(estimated)", "benef": "CumulativeWorldwideGross:$160,188,546"},
{"film": "Liaison fatale", "annee": "1987", "duree": "119 min", "director": "Adrian Lyne ", "note": "6.9", "budget": "Budget:$14,000,000(estimated)", "benef": "CumulativeWorldwideGross:$320,145,693"},
{"film": "Wall Street", "annee": "1987", "duree": "126 min", "director": "Oliver Stone ", "note": "7.4", "budget": "Budget:$15,000,000(estimated)", "benef": "CumulativeWorldwideGross:$43,848,069"},
{"film": "Voices of America: Hands Across America", "annee": "1986", "duree": "5 min", "director": "Perry Chasin, Bob Giraldi ", "note": "6.0", "budget": "None", "benef": "None"},
{"film": "Black Rain", "annee": "1989", "duree": "125 min", "director": "Ridley Scott ", "note": "6.7", "budget": "Budget:$30,000,000(estimated)", "benef": "CumulativeWorldwideGross:$134,212,055"},
{"film": "Billy Ocean: When the Going Gets Tough, the Tough Get Going", "annee": "1985", "duree": "4 min", "director": "Maurice Phillips ", "note": "7.4", "budget": "None", "benef": "None"},
{"film": "Chorus Line", "annee": "1985", "duree": "113 min", "director": "Richard Attenborough ", "note": "6.2", "budget": "Budget:$27,000,000(estimated)", "benef": "CumulativeWorldwideGross:$14,202,899"},
{"film": "Une lueur dans la nuit", "annee": "1992", "duree": "132 min", "director": "David Seltzer ", "note": "6.5", "budget": "None", "benef": "CumulativeWorldwideGross:$43,838,238"},
{"film": "La Nuit des juges", "annee": "1983", "duree": "109 min", "director": "Peter Hyams ", "note": "6.3", "budget": "None", "benef": "CumulativeWorldwideGross:$5,555,305"},
{"film": "\u00c0 la poursuite du diamant vert", "annee": "1984", "duree": "106 min", "director": "Robert Zemeckis ", "note": "6.9", "budget": "Budget:$10,000,000(estimated)", "benef": "CumulativeWorldwideGross:$86,572,238"},
{"film": "C'est ma chance", "annee": "1980", "duree": "None", "director": "Claudia Weill ", "note": "5.5", "budget": "None", "benef": "None"},
{"film": "Le diamant du Nil", "annee": "1985", "duree": "106 min", "director": "Lewis Teague ", "note": "6.2", "budget": "Budget:$25,000,000(estimated)", "benef": "CumulativeWorldwideGross:$96,773,200"},
{"film": "Morts suspectes", "annee": "1978", "duree": "113 min", "director": "Michael Crichton ", "note": "6.9", "budget": "Budget:$4,500,000(estimated)", "benef": "None"},
{"film": "Le vainqueur", "annee": "1979", "duree": "102 min", "director": "Steven Hilliard Stern ", "note": "5.9", "budget": "Budget:$3,600,000(estimated)", "benef": "CumulativeWorldwideGross:$6,012,556"},
{"film": "Le syndrome chinois", "annee": "1979", "duree": "122 min", "director": "James Bridges ", "note": "7.4", "budget": "Budget:$6,000,000(estimated)", "benef": "CumulativeWorldwideGross:$51,718,367"},
{"film": "Napol\u00e9on et Samantha", "annee": "1972", "duree": "92 min", "director": "Bernard McEveety ", "note": "6.1", "budget": "None", "benef": "None"},
{"film": "Adam at Six A.M.", "annee": "1970", "duree": "100 min", "director": "Robert Scheerer ", "note": "5.6", "budget": "None", "benef": "None"},
{"film": "When Michael Calls", "annee": "1972", "duree": "73 min", "director": "Philip Leacock ", "note": "6.2", "budget": "None", "benef": "None"},
{"film": "L'ombre d'un g\u00e9ant", "annee": "1966", "duree": "146 min", "director": "Melville Shavelson ", "note": "6.4", "budget": "None", "benef": "None"},
{"film": "Hail, Hero!", "annee": "1969", "duree": "100 min", "director": "David Miller ", "note": "5.5", "budget": "None", "benef": "None"},
{"film": "Summertree", "annee": "1971", "duree": "88 min", "director": "Anthony Newley ", "note": "5.7", "budget": "None", "benef": "None"}
]